CONTRIBUTING.rst
HISTORY.md
LICENSE
MANIFEST.in
README.md
setup.cfg
setup.py
docs/Makefile
docs/authors.rst
docs/conf.py
docs/contributing.rst
docs/history.rst
docs/index.rst
docs/installation.rst
docs/make.bat
docs/readme.rst
docs/usage.rst
testcube_client/__init__.py
testcube_client/business.py
testcube_client/cli.py
testcube_client/request_client.py
testcube_client/request_helper.py
testcube_client/result_parser.py
testcube_client/settings.py
testcube_client/utils.py
testcube_client/xunitparser.py
testcube_client.egg-info/PKG-INFO
testcube_client.egg-info/SOURCES.txt
testcube_client.egg-info/dependency_links.txt
testcube_client.egg-info/entry_points.txt
testcube_client.egg-info/not-zip-safe
testcube_client.egg-info/requires.txt
testcube_client.egg-info/top_level.txt
tests/__init__.py
tests/test_business.py
tests/test_fake.py
tests/test_real.py
tests/test_testcube_client_api.py
tests/default/__init__.py
tests/default/test_testcube_settings.py
tests/default/test_xunit_parser.py
tests/xunits/_utility_tests.py.xml
tests/xunits/example.py
tests/xunits/results.xml
tests/xunits/testcube.png