Metadata-Version: 2.1
Name: testcube-client
Version: 0.8.1
Summary: A Python client for testcube. (https://github.com/tobyqin/testcube)
Home-page: https://github.com/tobyqin/testcube-client
Author: Toby Qin
Author-email: toby.qin@live.com
License: MIT license
Keywords: testcube,testcube-client,test platform,test client
Platform: UNKNOWN
Classifier: Development Status :: 4 - Beta
Classifier: Intended Audience :: Developers
Classifier: License :: OSI Approved :: MIT License
Classifier: Natural Language :: English
Classifier: Programming Language :: Python :: 2.7
Classifier: Programming Language :: Python :: 3.5
